ndx_simulation_output/__init__.py
ndx_simulation_output/simulation_output.py
ndx_simulation_output/io/__init__.py
ndx_simulation_output/io/from_sonata.py
ndx_simulation_output/io/to_sonata.py
ndx_simulation_output/spec/ndx-simulation-output.extensions.yaml
ndx_simulation_output/spec/ndx-simulation-output.namespace.yaml
tests/__init__.py
tests/test_ndx_simulation_output.py
ndx_simulation_output-0.2.6.dist-info/LICENSE
ndx_simulation_output-0.2.6.dist-info/METADATA
ndx_simulation_output-0.2.6.dist-info/WHEEL
ndx_simulation_output-0.2.6.dist-info/top_level.txt
ndx_simulation_output-0.2.6.dist-info/RECORD
