Metadata-Version: 2.1
Name: ndx-simulation-output
Version: 0.2.6
Summary: Holds structures for recording data from multiple compartments of multiple neurons in a single TimeSeries
Home-page: UNKNOWN
Author: Ben Dichter
Author-email: ben.dichter@gmail.com
License: UNKNOWN
Platform: UNKNOWN
Classifier: Intended Audience :: Developers
Classifier: Intended Audience :: Science/Research
Requires-Dist: pynwb (>=1.1.2)
Requires-Dist: tqdm
